groundwork_spreadsheets/__init__.py
groundwork_spreadsheets/patterns/ExcelValidationPattern/__init__.py
groundwork_spreadsheets/patterns/ExcelValidationPattern/assets/excel_config_schema.json
groundwork_spreadsheets/patterns/ExcelValidationPattern/excel_validation_pattern.py
groundwork_spreadsheets/patterns/__init__.py
groundwork_spreadsheets-0.4.4.dist-info/LICENSE
groundwork_spreadsheets-0.4.4.dist-info/WHEEL
groundwork_spreadsheets-0.4.4.dist-info/METADATA
groundwork_spreadsheets-0.4.4.dist-info/RECORD
