Metadata-Version: 2.1
Name: groundwork-spreadsheets
Version: 0.4.4
Summary: Patterns for reading writing spreadsheet documents
Home-page: https://pypi.org/project/groundwork-spreadsheets/
License: MIT
Author: Marco Heinemann
Author-email: marco.heinemann@useblocks.com
Requires-Python: >=3.6,<4.0
Classifier: Development Status :: 5 - Production/Stable
Classifier: Intended Audience :: Developers
Classifier: License :: OSI Approved :: MIT License
Classifier: Operating System :: OS Independent
Classifier: Programming Language :: Python
Classifier: Programming Language :: Python :: 3
Classifier: Programming Language :: Python :: 3.6
Classifier: Programming Language :: Python :: 3.7
Classifier: Programming Language :: Python :: 3.8
Requires-Dist: groundwork (>=0.1.10)
Requires-Dist: jsonschema
Requires-Dist: openpyxl
Project-URL: Documentation, https://groundwork-spreadsheets.readthedocs.io/en/latest
Project-URL: Repository, https://github.com/useblocks/groundwork-spreadsheets
